[
    {
        "taxonomy":{
            "family": "family",
            "genus": "genus",
            "species": "species",
            "taxonAuthor":"species author",
            "infraRank":"subspecies",
            "infraTaxon":"subspecies author",
            "synonym":"true,false",
            "synOf":"id of synonym taxa"
        },
        "statusBiogeo": {
            "biogeoStatusLoc": "locality for the biogeographic status",
            "biogeoStatus": "(e=endemic,n=native,i=introduced"
            },
        "growthForm": "growth form"        
    }
]